gitreturntowork/__init__.py
gitreturntowork-0.0.5.dist-info/LICENSE
gitreturntowork-0.0.5.dist-info/WHEEL
gitreturntowork-0.0.5.dist-info/METADATA
gitreturntowork-0.0.5.dist-info/RECORD
