Metadata-Version: 2.1
Name: gitreturntowork
Version: 0.0.5
Summary: 
Author: Brighten Tompkins
Author-email: brightenqtompkins@gmail.com
Requires-Python: >=3.9,<4.0
Classifier: Programming Language :: Python :: 3
Classifier: Programming Language :: Python :: 3.10
Classifier: Programming Language :: Python :: 3.9
Requires-Dist: PyInquirer (>=1.0.3,<2.0.0)
